hs_social_listener/__init__.py
hs_social_listener/twitter_listener.py
hs_social_listener-1.7.dist-info/LICENSE
hs_social_listener-1.7.dist-info/METADATA
hs_social_listener-1.7.dist-info/WHEEL
hs_social_listener-1.7.dist-info/top_level.txt
hs_social_listener-1.7.dist-info/RECORD
