Metadata-Version: 2.1
Name: hs-social-listener
Version: 1.7
Summary: A library to analyse conversations on social media
Home-page: https://hearts-science.com
Author: James Londal
Author-email: UNKNOWN
License: GNU AFFERO GENERAL PUBLIC LICENSE
Platform: UNKNOWN
Requires-Dist: twint
Requires-Dist: pandas
Requires-Dist: numpy
Requires-Dist: nest-asyncio
Requires-Dist: textblob
